scribus_image_embedder/__init__.py
scribus_image_embedder/cli.py
scribus_image_embedder/embedder.py
scribus_image_embedder-1.0.5.dist-info/licenses/LICENSE
scribus_image_embedder-1.0.5.dist-info/METADATA
scribus_image_embedder-1.0.5.dist-info/WHEEL
scribus_image_embedder-1.0.5.dist-info/entry_points.txt
scribus_image_embedder-1.0.5.dist-info/top_level.txt
scribus_image_embedder-1.0.5.dist-info/RECORD
